mad_gui/__init__.py
mad_gui/components/__init__.py
mad_gui/components/dialogs/__init__.py
mad_gui/components/dialogs/data_selector.py
mad_gui/components/dialogs/label_annotation_dialog.py
mad_gui/components/dialogs/plugin_selection/__init__.py
mad_gui/components/dialogs/plugin_selection/load_data_dialog.py
mad_gui/components/dialogs/plugin_selection/plugin_selection_dialog.py
mad_gui/components/dialogs/user_information.py
mad_gui/components/helper.py
mad_gui/components/key_event_handler.py
mad_gui/components/sidebar.py
mad_gui/config/__init__.py
mad_gui/config/settings.py
mad_gui/config/theme.py
mad_gui/models/__init__.py
mad_gui/models/global_data.py
mad_gui/models/local/__init__.py
mad_gui/models/local/plot_data.py
mad_gui/models/ui_state.py
mad_gui/plot_tools/labels/__init__.py
mad_gui/plot_tools/labels/base_label.py
mad_gui/plot_tools/labels/labels.py
mad_gui/plot_tools/plots/__init__.py
mad_gui/plot_tools/plots/base_mode_handler.py
mad_gui/plot_tools/plots/base_plot.py
mad_gui/plot_tools/plots/sensor_plot.py
mad_gui/plot_tools/plots/sensor_plot_mode_handler.py
mad_gui/plot_tools/plots/video_plot.py
mad_gui/plot_tools/plots/video_plot_mode_handler.py
mad_gui/plugins/__init__.py
mad_gui/plugins/base.py
mad_gui/plugins/example.py
mad_gui/plugins/helper.py
mad_gui/qt_designer/__init__.py
mad_gui/qt_designer/channel_selector.ui
mad_gui/qt_designer/images/algorithm.png
mad_gui/qt_designer/images/burger.png
mad_gui/qt_designer/images/camera.png
mad_gui/qt_designer/images/camera_light.png
mad_gui/qt_designer/images/export.png
mad_gui/qt_designer/images/icon.png
mad_gui/qt_designer/images/label.png
mad_gui/qt_designer/images/logo_mad_man.png
mad_gui/qt_designer/images/open.png
mad_gui/qt_designer/images/reload.png
mad_gui/qt_designer/images/save.png
mad_gui/qt_designer/load.ui
mad_gui/qt_designer/main.ui
mad_gui/qt_designer/palette_btn.xml
mad_gui/qt_designer/palette_window.xml
mad_gui/qt_designer/plugin_selection.ui
mad_gui/qt_designer/ui_video.py
mad_gui-1.0.1.dist-info/entry_points.txt
mad_gui-1.0.1.dist-info/LICENSE
mad_gui-1.0.1.dist-info/WHEEL
mad_gui-1.0.1.dist-info/METADATA
mad_gui-1.0.1.dist-info/RECORD
