Metadata-Version: 2.1
Name: mad-gui
Version: 1.0.1
Summary: Python GUI for annotating and processing time series data.
Home-page: https://github.com/mad-lab-fau/mad-gui
Author: Malte Ollenschlaeger
Author-email: malte.ollenschlaeger@fau.de
Requires-Python: >=3.8,<3.10
Classifier: Intended Audience :: Science/Research
Classifier: Programming Language :: Python :: 3
Classifier: Programming Language :: Python :: 3.8
Classifier: Programming Language :: Python :: 3.9
Classifier: Topic :: Scientific/Engineering
Requires-Dist: PySide2 (==5.15.1)
Requires-Dist: pandas
Requires-Dist: pyqtgraph (==0.11.0)
Requires-Dist: python-vlc (>=3.0.16120,<4.0.0)
Requires-Dist: sphinx-qt-documentation (>=0.3,<0.4)
Requires-Dist: typing-extensions (>=3.10.0,<4.0.0)
Project-URL: Repository, https://github.com/mad-lab-fau/mad-gui
